cdisp
