Metadata-Version: 1.1
Name: cdisp
Version: 0.0.18
Summary: My personal support packages for dispersion and nonlinear optics analysis using COMSOL simulations
Home-page: https://github.com/fbarbosa/cdisp
Author: Felippe Barbosa
Author-email: felippe.barbosa@gmail.com
License: MIT v1.0
Keywords: dispersion COMSOL
Platform: OS Independent
Classifier: Topic :: Scientific/Engineering :: Physics
Classifier: Intended Audience :: Science/Research
Classifier: License :: OSI Approved :: Boost Software License 1.0 (BSL-1.0)
Provides: cdisp
